setup.py
importProject4/NewPerson.py
importProject4/clone.py
importProject5/1212.py
importProject5/NewPerson.py
importProject5/clone.py
realgroup.egg-info/PKG-INFO
realgroup.egg-info/SOURCES.txt
realgroup.egg-info/dependency_links.txt
realgroup.egg-info/requires.txt
realgroup.egg-info/top_level.txt