Metadata-Version: 2.1
Name: realgroup
Version: 1.0.0.10
Summary: ${Description}
Author: dyc
Author-email: your@email.com
